Metadata-Version: 1.2
Name: weeder
Version: 0.1
Summary: Remove unneeded historical files
Home-page: https://github.com/GambitResearch/weeder
Author: Daniele Varrazzo
Author-email: piro@gambitresearch.com
License: UNKNOWN
Project-URL: Bug Reports, https://github.com/GambitResearch/weeder/issues
Project-URL: Source, https://github.com/GambitResearch/weeder/
Keywords: backup sysadmin junk
Platform: UNKNOWN
Classifier: Development Status :: 4 - Beta
Classifier: Intended Audience :: Developers
Classifier: License :: OSI Approved :: MIT License
Classifier: Programming Language :: Python :: 3
Requires-Python: >=3.4, <4
